senti_key_summ.py
senti_key_summ-0.0.3.dist-info/METADATA
senti_key_summ-0.0.3.dist-info/WHEEL
senti_key_summ-0.0.3.dist-info/top_level.txt
senti_key_summ-0.0.3.dist-info/RECORD
